bilibili_beauty/__init__.py
bilibili_beauty/config.py
bilibili_beauty/main.py
bilibili_beauty-0.0.2.dist-info/LICENSE
bilibili_beauty-0.0.2.dist-info/METADATA
bilibili_beauty-0.0.2.dist-info/WHEEL
bilibili_beauty-0.0.2.dist-info/entry_points.txt
bilibili_beauty-0.0.2.dist-info/RECORD
